rpze/__init__.py
rpze/__main__.py
rpze/rp_extend.cp313-win_amd64.pyd
rpze/rp_extend.pyi
rpze/basic/__init__.py
rpze/basic/asm.py
rpze/basic/exception.py
rpze/basic/gridstr.py
rpze/basic/inject.py
rpze/bin/rp_dll.dll
rpze/bin/rp_injector.exe
rpze/examples/__init__.py
rpze/examples/botanical_clock.py
rpze/examples/dancing_example.py
rpze/examples/end_callback_example.py
rpze/examples/iztools_example.py
rpze/examples/pole_jumping_test.py
rpze/flow/__init__.py
rpze/flow/flow.py
rpze/flow/utils.py
rpze/iztest/__init__.py
rpze/iztest/cond_funcs.py
rpze/iztest/consts.py
rpze/iztest/dancing.py
rpze/iztest/iztest.py
rpze/iztest/operations.py
rpze/iztest/plant_modifier.py
rpze/iztest/sun_num_utils.py
rpze/structs/__init__.py
rpze/structs/game_board.py
rpze/structs/griditem.py
rpze/structs/obj_base.py
rpze/structs/plant.py
rpze/structs/projectile.py
rpze/structs/zombie.py
rpze-0.2.3.dist-info/METADATA
rpze-0.2.3.dist-info/WHEEL
rpze-0.2.3.dist-info/licenses/LICENSE.txt
rpze-0.2.3.dist-info/RECORD
