Metadata-Version: 2.1
Name: rpze
Version: 0.2.3
Summary: rpze: Remote Python, Zombie: Endless
Project-URL: Repository, https://github.com/ObeliskGate/rpze.git
Author: ObeliskGate
License-File: LICENSE.txt
Keywords: pvz
Classifier: Development Status :: 4 - Beta
Classifier: License :: OSI Approved :: GNU General Public License v3 (GPLv3)
Classifier: Natural Language :: Chinese (Simplified)
Classifier: Operating System :: Microsoft :: Windows
Requires-Python: >=3.11
Requires-Dist: keystone-engine>=0.9.2
